magicstr/__init__.py
magicstr/gspread_tools.py
magicstr/magicstr.py
magicstr/namestring.py
magicstr/template_strings.xml
magicstr/word.py
magicstr-3.78.data/scripts/magicstr
magicstr-3.78.dist-info/METADATA
magicstr-3.78.dist-info/WHEEL
magicstr-3.78.dist-info/top_level.txt
magicstr-3.78.dist-info/RECORD
